ytdlpy.py
easy_yt_dlp_py-1.0.0.dist-info/LICENSE
easy_yt_dlp_py-1.0.0.dist-info/METADATA
easy_yt_dlp_py-1.0.0.dist-info/WHEEL
easy_yt_dlp_py-1.0.0.dist-info/top_level.txt
easy_yt_dlp_py-1.0.0.dist-info/RECORD
