Metadata-Version: 2.1
Name: easy-yt-dlp-py
Version: 1.0.0
Summary: Easier yt-dlp download using in python
Author: Yarrtt
Classifier: Programming Language :: Python :: 3
Classifier: License :: OSI Approved :: MIT License
Classifier: Operating System :: OS Independent
Requires-Python: >=2.6.6
License-File: LICENSE
